sg_go.py
sggo/__init__.py
sggo/app.py
sggo/static/css/jquery.qtip.css
sggo/static/css/style.css
sggo/static/js/d3.js
sggo/static/js/dagre-d3.js
sggo/static/js/dagre.js
sggo/static/js/jquery.min.js
sggo/static/js/jquery.qtip.js
sggo/templates/graph.html
SgGo-0.7.0.dist-info/METADATA
SgGo-0.7.0.dist-info/WHEEL
SgGo-0.7.0.dist-info/entry_points.txt
SgGo-0.7.0.dist-info/top_level.txt
SgGo-0.7.0.dist-info/RECORD
