Metadata-Version: 2.1
Name: SgGo
Version: 0.7.0
Summary: view sg graph.
Home-page: UNKNOWN
Author: Wei Zou
Author-email: wei.zou@corerain.com
License: MIT
Platform: UNKNOWN
Requires-Dist: Flask
Requires-Dist: click (>=6.7)
